pypromotertools/__init__.py
pypromotertools/pypromotertools.py
pypromotertools-1.0.2.dist-info/LICENSE
pypromotertools-1.0.2.dist-info/METADATA
pypromotertools-1.0.2.dist-info/WHEEL
pypromotertools-1.0.2.dist-info/entry_points.txt
pypromotertools-1.0.2.dist-info/top_level.txt
pypromotertools-1.0.2.dist-info/RECORD
