Metadata-Version: 2.1
Name: pypromotertools
Version: 1.0.2
Summary: a collection of tools for acquiring gene promoters
Home-page: https://github.com/biomedicalpulsar/pypromotertools
Author: BiomedicalPulsar
Author-email: biomedicalpulsar@163.com
Classifier: Programming Language :: Python :: 3
Classifier: License :: OSI Approved :: MIT License
Classifier: Operating System :: OS Independent
License-File: LICENSE
